webpmin/__main__.py
webpmin/webpio.py
webpmin-1.1.4.dist-info/LICENSE
webpmin-1.1.4.dist-info/METADATA
webpmin-1.1.4.dist-info/WHEEL
webpmin-1.1.4.dist-info/entry_points.txt
webpmin-1.1.4.dist-info/top_level.txt
webpmin-1.1.4.dist-info/RECORD
